cmc_dataeng_internship_avneetkaur/__init__.py
cmc_dataeng_internship_avneetkaur/excercise13.py
cmc_dataeng_internship_avneetkaur-0.0.1.dist-info/LICENSE
cmc_dataeng_internship_avneetkaur-0.0.1.dist-info/METADATA
cmc_dataeng_internship_avneetkaur-0.0.1.dist-info/WHEEL
cmc_dataeng_internship_avneetkaur-0.0.1.dist-info/top_level.txt
cmc_dataeng_internship_avneetkaur-0.0.1.dist-info/RECORD
