Metadata-Version: 2.1
Name: cmc-dataeng-internship-avneetkaur
Version: 0.0.1
Summary: Package for Excercise 13
Home-page: UNKNOWN
Author: Avneet Kaur
Author-email: <avneet14027@iiitd.ac.in>
License: UNKNOWN
Keywords: python,first package
Platform: UNKNOWN
Classifier: Development Status :: 3 - Alpha
Classifier: Intended Audience :: Education
Classifier: Programming Language :: Python :: 2
Classifier: Programming Language :: Python :: 3
Classifier: Operating System :: MacOS :: MacOS X
Classifier: Operating System :: Microsoft :: Windows
